pinecone_db_construct/__init__.py
pinecone_db_construct/py.typed
pinecone_db_construct/_jsii/__init__.py
pinecone_db_construct/_jsii/pinecone-db-construct@0.0.10.jsii.tgz
pinecone_db_construct-0.0.10.dist-info/LICENSE
pinecone_db_construct-0.0.10.dist-info/METADATA
pinecone_db_construct-0.0.10.dist-info/WHEEL
pinecone_db_construct-0.0.10.dist-info/top_level.txt
pinecone_db_construct-0.0.10.dist-info/RECORD
