Metadata-Version: 2.1
Name: pinecone-db-construct
Version: 0.0.10
Summary: A CDK construct for Pinecone Indexes
Home-page: https://github.com/petterle-endeavors/pinecone-db-construct
Author: Jacob Petterle<jacobpetterle@gmail.com>
License: MIT
Project-URL: Source, https://github.com/petterle-endeavors/pinecone-db-construct
Classifier: Intended Audience :: Developers
Classifier: Operating System :: OS Independent
Classifier: Programming Language :: JavaScript
Classifier: Programming Language :: Python :: 3 :: Only
Classifier: Programming Language :: Python :: 3.8
Classifier: Programming Language :: Python :: 3.9
Classifier: Programming Language :: Python :: 3.10
Classifier: Programming Language :: Python :: 3.11
Classifier: Typing :: Typed
Classifier: Development Status :: 4 - Beta
Classifier: License :: OSI Approved
Requires-Python: ~=3.8
License-File: LICENSE
Requires-Dist: aws-cdk-lib <3.0.0,>=2.118.0
Requires-Dist: aws-cdk.aws-lambda-python-alpha <3.0.0,>=2.100.0.a0
Requires-Dist: constructs <11.0.0,>=10.0.5
Requires-Dist: jsii <2.0.0,>=1.94.0
Requires-Dist: publication >=0.0.3
Requires-Dist: typeguard ~=2.13.3
